ez_validate/__init__.py
ez_validate/floatvalidator.py
ez_validate/functions.py
ez_validate/intvalidator.py
ez_validate/listvalidator.py
ez_validate/pathvalidator.py
ez_validate/strvalidator.py
ez_validate/validatethat.py
ez_validate/validationerror.py
ez_validate-0.1.0.dist-info/LICENSE
ez_validate-0.1.0.dist-info/METADATA
ez_validate-0.1.0.dist-info/WHEEL
ez_validate-0.1.0.dist-info/top_level.txt
ez_validate-0.1.0.dist-info/RECORD
