Metadata-Version: 2.1
Name: ez_validate
Version: 0.1.0
Summary: Builder-like data validation package
Author-email: OLODiman11 <olodiman11@mail.ru>
Classifier: Programming Language :: Python :: 2
Classifier: License :: OSI Approved :: MIT License
Classifier: Operating System :: OS Independent
Requires-Python: >=2.7
License-File: LICENSE
